boosty/__init__.py
boosty/api/__init__.py
boosty/api/api.py
boosty/api/auth/__init__.py
boosty/api/auth/auth.py
boosty/api/auth/resolvers/__init__.py
boosty/api/auth/resolvers/abc.py
boosty/api/auth/resolvers/file.py
boosty/types/__init__.py
boosty/types/base.py
boosty/types/blacklist.py
boosty/types/comment.py
boosty/types/common.py
boosty/types/content.py
boosty/types/counters.py
boosty/types/deferred_access.py
boosty/types/donator.py
boosty/types/media_types.py
boosty/types/poll.py
boosty/types/post.py
boosty/types/reaction_counters.py
boosty/types/reactions.py
boosty/types/reply.py
boosty/types/teaser.py
boosty/types/users.py
boosty/utils/__init__.py
boosty/utils/browser_login.py
boosty/utils/client.py
boosty/utils/consts.py
boosty/utils/post.py
boosty/utils/types.py
boosty/utils/video.py
boosty-0.0.35.dist-info/METADATA
boosty-0.0.35.dist-info/WHEEL
boosty-0.0.35.dist-info/licenses/LICENSE
boosty-0.0.35.dist-info/RECORD
