Metadata-Version: 2.4
Name: boosty
Version: 0.0.35
Summary: Asynchronous boosty wrapper with some utils
Project-URL: Documentation, https://github.com/barsikus007/boosty#readme
Project-URL: Issues, https://github.com/barsikus007/boosty/issues
Project-URL: Source, https://github.com/barsikus007/boosty
Author: barsikus007
License-Expression: MIT
License-File: LICENSE
Keywords: asyncio,boosty,wrapper
Classifier: Development Status :: 4 - Beta
Classifier: Programming Language :: Python
Classifier: Programming Language :: Python :: 3.10
Classifier: Programming Language :: Python :: 3.11
Classifier: Programming Language :: Python :: 3.12
Classifier: Programming Language :: Python :: 3.13
Classifier: Programming Language :: Python :: Implementation :: CPython
Classifier: Programming Language :: Python :: Implementation :: PyPy
Requires-Python: >=3.10
Requires-Dist: aiohttp~=3.9
Requires-Dist: pydantic[email]~=2.8
Provides-Extra: all
Requires-Dist: aiohttp[speedups]~=3.9; extra == 'all'
Requires-Dist: playwright~=1.48; extra == 'all'
Provides-Extra: browser
Requires-Dist: playwright~=1.48; extra == 'browser'
Provides-Extra: fast
Requires-Dist: aiohttp[speedups]~=3.9; extra == 'fast'
